.gitignore
LICENSE
MANIFEST.in
README.md
setup.py
translate_odf.epj
doc/Doxyfile
doc/index.dox
locale/es.po
locale/translate_odf.pot
translate_odf/__init__.py
translate_odf/translate_odf.py
translate_odf/version.py
translate_odf.egg-info/PKG-INFO
translate_odf.egg-info/SOURCES.txt
translate_odf.egg-info/dependency_links.txt
translate_odf.egg-info/entry_points.txt
translate_odf.egg-info/not-zip-safe
translate_odf.egg-info/requires.txt
translate_odf.egg-info/top_level.txt
translate_odf/images/translate_odf.png
translate_odf/images/translate_odf_doxygen.png
translate_odf/locale/es/LC_MESSAGES/translate_odf.mo
translate_odf/reusing/file_functions.py