Metadata-Version: 2.1
Name: translate-odf
Version: 0.3.0
Summary: Command to translate Libreoffice ODF files with odf2xliff
Home-page: https://github.com/turulomio/translate_odf
Author: Turulomio
Author-email: turulomio@yahoo.es
License: GPL-3
Keywords: translate odf odt ods odp libreoffice
Platform: UNKNOWN
Classifier: Development Status :: 4 - Beta
Classifier: Intended Audience :: Developers
Classifier: Topic :: Software Development :: Build Tools
Classifier: License :: OSI Approved :: GNU General Public License v3 (GPLv3)
Classifier: Programming Language :: Python :: 3
License-File: LICENSE
